Dhelpers/SingleInstance.py
Dhelpers/__init__.py
Dhelpers/all.py
Dhelpers/arghandling.py
Dhelpers/baseclasses.py
Dhelpers/container.py
Dhelpers/counting.py
Dhelpers/crypt.py
Dhelpers/decorators.py
Dhelpers/external.py
Dhelpers/file_iteration.py
Dhelpers/importtools.py
Dhelpers/launcher.py
Dhelpers/linux_checks.py
Dhelpers/named.py
Dhelpers/platform.py
Dhelpers/psutil_fix.py
Dhelpers/sphinx_docs.py
Dhelpers/strhandling.py
Dhelpers/KeyboardLayouts/__init__.py
Dhelpers/KeyboardLayouts/layouts_imported_from_xkb/__init__.py
Dhelpers/KeyboardLayouts/layouts_imported_from_xkb/al.json
Dhelpers/KeyboardLayouts/layouts_imported_from_xkb/am.json
Dhelpers/KeyboardLayouts/layouts_imported_from_xkb/apl.json
Dhelpers/KeyboardLayouts/layouts_imported_from_xkb/at.json
Dhelpers/KeyboardLayouts/layouts_imported_from_xkb/au.json
Dhelpers/KeyboardLayouts/layouts_imported_from_xkb/base.json
Dhelpers/KeyboardLayouts/layouts_imported_from_xkb/be.json
Dhelpers/KeyboardLayouts/layouts_imported_from_xkb/bt.json
Dhelpers/KeyboardLayouts/layouts_imported_from_xkb/by.json
Dhelpers/KeyboardLayouts/layouts_imported_from_xkb/cd.json
Dhelpers/KeyboardLayouts/layouts_imported_from_xkb/ch.json
Dhelpers/KeyboardLayouts/layouts_imported_from_xkb/cm.json
Dhelpers/KeyboardLayouts/layouts_imported_from_xkb/cn.json
Dhelpers/KeyboardLayouts/layouts_imported_from_xkb/de.json
Dhelpers/KeyboardLayouts/layouts_imported_from_xkb/dk.json
Dhelpers/KeyboardLayouts/layouts_imported_from_xkb/ee.json
Dhelpers/KeyboardLayouts/layouts_imported_from_xkb/epo.json
Dhelpers/KeyboardLayouts/layouts_imported_from_xkb/es.json
Dhelpers/KeyboardLayouts/layouts_imported_from_xkb/fo.json
Dhelpers/KeyboardLayouts/layouts_imported_from_xkb/fr.json
Dhelpers/KeyboardLayouts/layouts_imported_from_xkb/ge.json
Dhelpers/KeyboardLayouts/layouts_imported_from_xkb/gh.json
Dhelpers/KeyboardLayouts/layouts_imported_from_xkb/gn.json
Dhelpers/KeyboardLayouts/layouts_imported_from_xkb/hu.json
Dhelpers-0.1.6.dist-info/COPYING
Dhelpers-0.1.6.dist-info/METADATA
Dhelpers-0.1.6.dist-info/WHEEL
Dhelpers-0.1.6.dist-info/top_level.txt
Dhelpers-0.1.6.dist-info/RECORD
