Metadata-Version: 2.1
Name: Dhelpers
Version: 0.1.6
Summary: Dhelpers support modules
Home-page: https://github.com/dp0s/Dpowers
Author: DPS
Author-email: dps@my.mail.de
Classifier: Programming Language :: Python :: 3
Classifier: License :: OSI Approved :: GNU General Public License v3 (GPLv3)
Requires-Python: >=3.6
License-File: COPYING
Requires-Dist: psutil >=5.4.2
Requires-Dist: pyyaml >=3.12
Requires-Dist: setuptools >=45
